wattrex_driver_flow/__init__.py
wattrex_driver_flow/__version__.py
wattrex_driver_flow/drv_flow.py
wattrex_driver_flow-0.0.3.dist-info/LICENSE.txt
wattrex_driver_flow-0.0.3.dist-info/METADATA
wattrex_driver_flow-0.0.3.dist-info/WHEEL
wattrex_driver_flow-0.0.3.dist-info/top_level.txt
wattrex_driver_flow-0.0.3.dist-info/RECORD
